MANIFEST.in
README.txt
setup.cfg
setup.py
atreal/__init__.py
atreal/__init__.pyc
atreal.richfile.streaming.egg-info/PKG-INFO
atreal.richfile.streaming.egg-info/SOURCES.txt
atreal.richfile.streaming.egg-info/dependency_links.txt
atreal.richfile.streaming.egg-info/entry_points.txt
atreal.richfile.streaming.egg-info/namespace_packages.txt
atreal.richfile.streaming.egg-info/not-zip-safe
atreal.richfile.streaming.egg-info/requires.txt
atreal.richfile.streaming.egg-info/top_level.txt
atreal/richfile/__init__.py
atreal/richfile/__init__.pyc
atreal/richfile/streaming/__init__.py
atreal/richfile/streaming/adapters.py
atreal/richfile/streaming/configure.zcml
atreal/richfile/streaming/convert.py
atreal/richfile/streaming/events.py
atreal/richfile/streaming/interfaces.py
atreal/richfile/streaming/browser/__init__.py
atreal/richfile/streaming/browser/configure.zcml
atreal/richfile/streaming/browser/controlpanel.pt
atreal/richfile/streaming/browser/controlpanel.py
atreal/richfile/streaming/browser/flowplayer.pt
atreal/richfile/streaming/browser/richfilestreaming_icon.png
atreal/richfile/streaming/browser/streaming.kss
atreal/richfile/streaming/browser/viewlets.py
atreal/richfile/streaming/browser/views.py
atreal/richfile/streaming/locales/atreal.richfile.streaming.pot
atreal/richfile/streaming/locales/fr/LC_MESSAGES/atreal.richfile.streaming.po
atreal/richfile/streaming/profiles/default/actionicons.xml
atreal/richfile/streaming/profiles/default/browserlayer.xml
atreal/richfile/streaming/profiles/default/componentregistry.xml
atreal/richfile/streaming/profiles/default/controlpanel.xml
atreal/richfile/streaming/profiles/default/kssregistry.xml
atreal/richfile/streaming/profiles/default/metadata.xml
atreal/richfile/streaming/profiles/default/skins.xml
atreal/richfile/streaming/skins/atreal_richfile_streaming/flowplayer-3.1.1.min.js
atreal/richfile/streaming/skins/atreal_richfile_streaming/flowplayer-3.1.1.swf
atreal/richfile/streaming/skins/atreal_richfile_streaming/flowplayer.audio-3.1.0.swf
atreal/richfile/streaming/skins/atreal_richfile_streaming/flowplayer.controls-3.1.1.swf