Metadata-Version: 1.0
Name: atreal.richfile.streaming
Version: 1.0.0beta2
Summary: Streaming Support Plugin for RichFileQualifier
Home-page: http://www.atreal.net/
Author: atReal
Author-email: contact@atreal.net
License: GPL
Keywords: plone richfile atreal streaming
Platform: UNKNOWN
Classifier: Framework :: Plone
Classifier: Programming Language :: Python
Classifier: Topic :: Software Development :: Libraries :: Python Modules
